leer_vm/__init__.py
leer_vm/opcodes.py
leer_vm/opfuncs.py
leer_vm/utils.py
leer_vm/vm.py
leer_vm-1.1.dist-info/METADATA
leer_vm-1.1.dist-info/WHEEL
leer_vm-1.1.dist-info/top_level.txt
leer_vm-1.1.dist-info/RECORD
