Metadata-Version: 2.1
Name: leer-vm
Version: 1.1
Summary: Virtual Machine for leer cryptocurrency
Home-page: https://github.com/WTRMQDev/VM
Author: Crez Khansick
Author-email: TetsuwanAtomu@tuta.io
License: UNKNOWN
Platform: UNKNOWN
Classifier: Programming Language :: Python :: 3
Classifier: Development Status :: 4 - Beta
Classifier: Intended Audience :: Developers
Classifier: License :: OSI Approved :: MIT License
Classifier: Operating System :: OS Independent
Requires-Dist: secp256k1-zkp (>=0.14.3)
Requires-Dist: sha3
